{
  "kind": "collectionType",
  "collectionName": "educations_and_trainings",
  "info": {
    "singularName": "education-and-training",
    "pluralName": "educations-and-trainings",
    "displayName": "Education and training",
    "description": ""
  },
  "options": {
    "draftAndPublish": true
  },
  "pluginOptions": {
    "i18n": {
      "localized": true
    }
  },
  "attributes": {
    "title": {
      "type": "string",
      "pluginOptions": {
        "i18n": {
          "localized": true
        }
      }
    },
    "company_name": {
      "type": "string",
      "pluginOptions": {
        "i18n": {
          "localized": true
        }
      }
    },
    "company_website": {
      "type": "string",
      "pluginOptions": {
        "i18n": {
          "localized": true
        }
      }
    },
    "start_date": {
      "type": "date",
      "pluginOptions": {
        "i18n": {
          "localized": false
        }
      }
    },
    "end_date": {
      "type": "date",
      "pluginOptions": {
        "i18n": {
          "localized": false
        }
      },
      "required": false
    },
    "graduating_certification": {
      "type": "string",
      "pluginOptions": {
        "i18n": {
          "localized": true
        }
      }
    },
    "slug": {
      "type": "uid",
      "pluginOptions": {
        "i18n": {
          "localized": true
        }
      },
      "targetField": "title",
      "required": true
    },
    "description": {
      "type": "customField",
      "pluginOptions": {
        "i18n": {
          "localized": true
        }
      },
      "customField": "plugin::ckeditor5.CKEditor",
      "options": {
        "preset": "defaultHtml"
      }
    }
  }
}
